[{"episode":514,"start_date":"15/05/2014","start_time":"14:00:00:00","gameTitle":"TEST - Acton-Boxborough vs. Somerville"},
 {"episode":514,"start_date":"15/05/2014","start_time":"14:30:00:00","gameTitle":"TEST - Acton-Boxborough vs. Somerville"},
 {"episode":514,"start_date":"15/05/2014","start_time":"15:00:00:00","gameTitle":"TEST - Acton-Boxborough vs. Somerville"},
 {"episode":514,"start_date":"15/05/2014","start_time":"15:30:00:00","gameTitle":"TEST - Acton-Boxborough vs. Somerville"},
 {"episode":514,"start_date":"16/05/2014","start_time":"10:30:00:00","gameTitle":"TEST - Acton-Boxborough vs. Somerville"},
 {"episode":514,"start_date":"16/05/2014","start_time":"11:00:00:00","gameTitle":"TEST - Acton-Boxborough vs. Somerville"},
 {"episode":514,"start_date":"16/05/2014","start_time":"11:30:00:00","gameTitle":"TEST - Acton-Boxborough vs. Somerville"},
 {"episode":514,"start_date":"16/05/2014","start_time":"12:00:00:00","gameTitle":"TEST - Acton-Boxborough vs. Somerville"},
 {"episode":514,"start_date":"16/05/2014","start_time":"13:00:00:00","gameTitle":"TEST - Acton-Boxborough vs. Somerville"},
 {"episode":514,"start_date":"16/05/2014","start_time":"13:30:00:00","gameTitle":"TEST - Acton-Boxborough vs. Somerville"},
 {"episode":514,"start_date":"16/05/2014","start_time":"14:00:00:00","gameTitle":"TEST - Acton-Boxborough vs. Somerville"},
 {"episode":514,"start_date":"16/05/2014","start_time":"14:30:00:00","gameTitle":"TEST - Acton-Boxborough vs. Somerville"},
 {"episode":514,"start_date":"16/05/2014","start_time":"15:00:00:00","gameTitle":"TEST - Acton-Boxborough vs. Somerville"}]
