[{"episode":0,"start_date":"05/04/2014","start_time":"18:00:00:00","gameTitle":"Baseball Edition","channel":"WGBH 2"},
 {"episode":0,"start_date":"05/04/2014","start_time":"22:00:00:00","gameTitle":"Baseball Edition","channel":"WGBH 2"},
 {"episode":0,"start_date":"05/04/2014","start_time":"23:00:00:00","gameTitle":"Baseball Edition","channel":"WGBX 44"},
 {"episode":0,"start_date":"06/04/2014","start_time":"10:00:00:00","gameTitle":"Baseball Edition","channel":"WGBH 2"},
 {"episode":0,"start_date":"06/04/2014","start_time":"17:00:00:00","gameTitle":"Baseball Edition","channel":"WGBH 2"},
 {"episode":501,"start_date":"06/04/2014","start_time":"12:00:00:00","gameTitle":"Adv. Math & Science Academy vs. Mystic Valley","channel":"WGBH 2"},
 {"episode":502,"start_date":"06/04/2014","start_time":"12:30:00:00","gameTitle":"Dover-Sherborn vs. Lexington","channel":"WGBH 2"},
 {"episode":503,"start_date":"06/04/2014","start_time":"13:00:00:00","gameTitle":"Chelmsford vs. Rockport","channel":"WGBH 2"},
 {"episode":504,"start_date":"06/04/2014","start_time":"13:30:00:00","gameTitle":"Newton North vs. Westford Academy","channel":"WGBH 2"},
 {"episode":505,"start_date":"06/04/2014","start_time":"14:00:00:00","gameTitle":"Nantucket vs. Somerville","channel":"WGBH 2"},
 {"episode":506,"start_date":"06/04/2014","start_time":"14:30:00:00","gameTitle":"Hingham vs. Sharon","channel":"WGBH 2"},
 {"episode":507,"start_date":"06/04/2014","start_time":"15:00:00:00","gameTitle":"Acton-Boxborough vs. Longmeadow","channel":"WGBH 2"},
 {"episode":508,"start_date":"06/04/2014","start_time":"15:30:00:00","gameTitle":"Arlington vs. Dartmouth","channel":"WGBH 2"},
 {"episode":0,"start_date":"06/04/2014","start_time":"16:00:00:00","gameTitle":"Baseball Edition","channel":"WGBX 44"},
 {"episode":0,"start_date":"07/04/2014","start_time":"02:30:00:00","gameTitle":"Baseball Edition","channel":"GBH Kids"},
 {"episode":0,"start_date":"07/04/2014","start_time":"20:30:00:00","gameTitle":"Baseball Edition","channel":"GBH Kids"},
 {"episode":0,"start_date":"07/04/2014","start_time":"23:30:00:00","gameTitle":"Baseball Edition","channel":"GBH Kids"},
 {"episode":0,"start_date":"08/04/2014","start_time":"16:30:00:00","gameTitle":"Baseball Edition","channel":"WGBH 2"},
 {"episode":0,"start_date":"08/04/2014","start_time":"16:30:00:00","gameTitle":"Baseball Edition","channel":"NHPTV Prime"},
 {"episode":0,"start_date":"09/04/2014","start_time":"02:30:00:00","gameTitle":"Baseball Edition","channel":"GBH Kids"},
 {"episode":0,"start_date":"09/04/2014","start_time":"20:30:00:00","gameTitle":"Baseball Edition","channel":"GBH Kids"},
 {"episode":0,"start_date":"09/04/2014","start_time":"23:30:00:00","gameTitle":"Baseball Edition","channel":"GBH Kids"},
 {"episode":0,"start_date":"11/04/2014","start_time":"07:30:00:00","gameTitle":"Baseball Edition","channel":"WGBX 44"},
 {"episode":509,"start_date":"12/04/2014","start_time":"18:00:00:00","gameTitle":"Adv. Math & Science Academy vs. Lexington","channel":"WGBH 2"},
 {"episode":509,"start_date":"12/04/2014","start_time":"23:00:00:00","gameTitle":"Adv. Math & Science Academy vs. Lexington","channel":"WGBX 44"},
 {"episode":509,"start_date":"13/04/2014","start_time":"10:00:00:00","gameTitle":"Adv. Math & Science Academy vs. Lexington","channel":"WGBH 2"},
 {"episode":509,"start_date":"13/04/2014","start_time":"17:00:00:00","gameTitle":"Adv. Math & Science Academy vs. Lexington","channel":"WGBH 2"},
 {"episode":509,"start_date":"14/04/2014","start_time":"02:30:00:00","gameTitle":"Adv. Math & Science Academy vs. Lexington","channel":"GBH Kids"},
 {"episode":509,"start_date":"14/04/2014","start_time":"20:30:00:00","gameTitle":"Adv. Math & Science Academy vs. Lexington","channel":"GBH Kids"},
 {"episode":509,"start_date":"14/04/2014","start_time":"23:30:00:00","gameTitle":"Adv. Math & Science Academy vs. Lexington","channel":"GBH Kids"},
 {"episode":509,"start_date":"15/04/2014","start_time":"16:30:00:00","gameTitle":"Adv. Math & Science Academy vs. Lexington","channel":"WGBH 2"},
 {"episode":509,"start_date":"15/04/2014","start_time":"16:30:00:00","gameTitle":"Adv. Math & Science Academy vs. Lexington","channel":"NHPTV Prime"},
 {"episode":509,"start_date":"16/04/2014","start_time":"02:30:00:00","gameTitle":"Adv. Math & Science Academy vs. Lexington","channel":"GBH Kids"},
 {"episode":509,"start_date":"16/04/2014","start_time":"20:30:00:00","gameTitle":"Adv. Math & Science Academy vs. Lexington","channel":"GBH Kids"},
 {"episode":509,"start_date":"16/04/2014","start_time":"23:30:00:00","gameTitle":"Adv. Math & Science Academy vs. Lexington","channel":"GBH Kids"},
 {"episode":509,"start_date":"18/04/2014","start_time":"07:30:00:00","gameTitle":"Adv. Math & Science Academy vs. Lexington","channel":"WGBX 44"},
 {"episode":510,"start_date":"19/04/2014","start_time":"18:00:00:00","gameTitle":"Newton North vs. Rockport","channel":"WGBH 2"},
 {"episode":510,"start_date":"19/04/2014","start_time":"23:00:00:00","gameTitle":"Newton North vs. Rockport","channel":"WGBX 44"},
 {"episode":510,"start_date":"20/04/2014","start_time":"10:00:00:00","gameTitle":"Newton North vs. Rockport","channel":"WGBH 2"},
 {"episode":510,"start_date":"20/04/2014","start_time":"17:00:00:00","gameTitle":"Newton North vs. Rockport","channel":"WGBH 2"},
 {"episode":510,"start_date":"21/04/2014","start_time":"02:30:00:00","gameTitle":"Newton North vs. Rockport","channel":"GBH Kids"},
 {"episode":510,"start_date":"21/04/2014","start_time":"20:30:00:00","gameTitle":"Newton North vs. Rockport","channel":"GBH Kids"},
 {"episode":510,"start_date":"21/04/2014","start_time":"23:30:00:00","gameTitle":"Newton North vs. Rockport","channel":"GBH Kids"},
 {"episode":510,"start_date":"22/04/2014","start_time":"16:30:00:00","gameTitle":"Newton North vs. Rockport","channel":"WGBH 2"},
 {"episode":510,"start_date":"22/04/2014","start_time":"16:30:00:00","gameTitle":"Newton North vs. Rockport","channel":"NHPTV Prime"},
 {"episode":510,"start_date":"23/04/2014","start_time":"02:30:00:00","gameTitle":"Newton North vs. Rockport","channel":"GBH Kids"},
 {"episode":510,"start_date":"23/04/2014","start_time":"20:30:00:00","gameTitle":"Newton North vs. Rockport","channel":"GBH Kids"},
 {"episode":510,"start_date":"23/04/2014","start_time":"23:30:00:00","gameTitle":"Newton North vs. Rockport","channel":"GBH Kids"},
 {"episode":510,"start_date":"25/04/2014","start_time":"07:30:00:00","gameTitle":"Newton North vs. Rockport","channel":"WGBX 44"},
 {"episode":511,"start_date":"26/04/2014","start_time":"18:00:00:00","gameTitle":"Sharon vs. Somerville","channel":"WGBH 2"},
 {"episode":511,"start_date":"26/04/2014","start_time":"23:00:00:00","gameTitle":"Sharon vs. Somerville","channel":"WGBX 44"},
 {"episode":511,"start_date":"27/04/2014","start_time":"10:00:00:00","gameTitle":"Sharon vs. Somerville","channel":"WGBH 2"},
 {"episode":511,"start_date":"27/04/2014","start_time":"17:00:00:00","gameTitle":"Sharon vs. Somerville","channel":"WGBH 2"},
 {"episode":511,"start_date":"28/04/2014","start_time":"02:30:00:00","gameTitle":"Sharon vs. Somerville","channel":"GBH Kids"},
 {"episode":511,"start_date":"28/04/2014","start_time":"20:30:00:00","gameTitle":"Sharon vs. Somerville","channel":"GBH Kids"},
 {"episode":511,"start_date":"28/04/2014","start_time":"23:30:00:00","gameTitle":"Sharon vs. Somerville","channel":"GBH Kids"},
 {"episode":511,"start_date":"29/04/2014","start_time":"16:30:00:00","gameTitle":"Sharon vs. Somerville","channel":"WGBH 2"},
 {"episode":511,"start_date":"29/04/2014","start_time":"16:30:00:00","gameTitle":"Sharon vs. Somerville","channel":"NHPTV Prime"},
 {"episode":511,"start_date":"30/04/2014","start_time":"02:30:00:00","gameTitle":"Sharon vs. Somerville","channel":"GBH Kids"},
 {"episode":511,"start_date":"30/04/2014","start_time":"20:30:00:00","gameTitle":"Sharon vs. Somerville","channel":"GBH Kids"},
 {"episode":511,"start_date":"30/04/2014","start_time":"23:30:00:00","gameTitle":"Sharon vs. Somerville","channel":"GBH Kids"},
 {"episode":511,"start_date":"02/05/2014","start_time":"07:30:00:00","gameTitle":"Sharon vs. Somerville","channel":"WGBX 44"},
 {"episode":512,"start_date":"03/05/2014","start_time":"18:00:00:00","gameTitle":"Acton-Boxborough vs. Arlington","channel":"WGBH 2"},
 {"episode":512,"start_date":"03/05/2014","start_time":"23:00:00:00","gameTitle":"Acton-Boxborough vs. Arlington","channel":"WGBX 44"},
 {"episode":512,"start_date":"04/05/2014","start_time":"10:00:00:00","gameTitle":"Acton-Boxborough vs. Arlington","channel":"WGBH 2"},
 {"episode":512,"start_date":"04/05/2014","start_time":"17:00:00:00","gameTitle":"Acton-Boxborough vs. Arlington","channel":"WGBH 2"},
 {"episode":512,"start_date":"05/05/2014","start_time":"02:30:00:00","gameTitle":"Acton-Boxborough vs. Arlington","channel":"GBH Kids"},
 {"episode":512,"start_date":"05/05/2014","start_time":"20:30:00:00","gameTitle":"Acton-Boxborough vs. Arlington","channel":"GBH Kids"},
 {"episode":512,"start_date":"05/05/2014","start_time":"23:30:00:00","gameTitle":"Acton-Boxborough vs. Arlington","channel":"GBH Kids"},
 {"episode":512,"start_date":"06/05/2014","start_time":"16:30:00:00","gameTitle":"Acton-Boxborough vs. Arlington","channel":"WGBH 2"},
 {"episode":512,"start_date":"06/05/2014","start_time":"16:30:00:00","gameTitle":"Acton-Boxborough vs. Arlington","channel":"NHPTV Prime"},
 {"episode":512,"start_date":"07/05/2014","start_time":"02:30:00:00","gameTitle":"Acton-Boxborough vs. Arlington","channel":"GBH Kids"},
 {"episode":512,"start_date":"07/05/2014","start_time":"20:30:00:00","gameTitle":"Acton-Boxborough vs. Arlington","channel":"GBH Kids"},
 {"episode":512,"start_date":"07/05/2014","start_time":"23:30:00:00","gameTitle":"Acton-Boxborough vs. Arlington","channel":"GBH Kids"},
 {"episode":512,"start_date":"09/05/2014","start_time":"07:30:00:00","gameTitle":"Acton-Boxborough vs. Arlington","channel":"WGBX 44"},
 {"episode":513,"start_date":"10/05/2014","start_time":"18:00:00:00","gameTitle":"Lexington vs. Newton North","channel":"WGBH 2"},
 {"episode":513,"start_date":"10/05/2014","start_time":"23:00:00:00","gameTitle":"Lexington vs. Newton North","channel":"WGBX 44"},
 {"episode":513,"start_date":"11/05/2014","start_time":"10:00:00:00","gameTitle":"Lexington vs. Newton North","channel":"WGBH 2"},
 {"episode":513,"start_date":"11/05/2014","start_time":"17:00:00:00","gameTitle":"Lexington vs. Newton North","channel":"WGBH 2"},
 {"episode":513,"start_date":"12/05/2014","start_time":"02:30:00:00","gameTitle":"Lexington vs. Newton North","channel":"GBH Kids"},
 {"episode":513,"start_date":"12/05/2014","start_time":"20:30:00:00","gameTitle":"Lexington vs. Newton North","channel":"GBH Kids"},
 {"episode":513,"start_date":"12/05/2014","start_time":"23:30:00:00","gameTitle":"Lexington vs. Newton North","channel":"GBH Kids"},
 {"episode":513,"start_date":"13/05/2014","start_time":"16:30:00:00","gameTitle":"Lexington vs. Newton North","channel":"WGBH 2"},
 {"episode":513,"start_date":"13/05/2014","start_time":"16:30:00:00","gameTitle":"Lexington vs. Newton North","channel":"NHPTV Prime"},
 {"episode":513,"start_date":"14/05/2014","start_time":"02:30:00:00","gameTitle":"Lexington vs. Newton North","channel":"GBH Kids"},
 {"episode":513,"start_date":"14/05/2014","start_time":"20:30:00:00","gameTitle":"Lexington vs. Newton North","channel":"GBH Kids"},
 {"episode":513,"start_date":"14/05/2014","start_time":"23:30:00:00","gameTitle":"Lexington vs. Newton North","channel":"GBH Kids"},
 {"episode":513,"start_date":"16/05/2014","start_time":"07:30:00:00","gameTitle":"Lexington vs. Newton North","channel":"WGBX 44"},
 {"episode":514,"start_date":"17/05/2014","start_time":"18:00:00:00","gameTitle":"Acton-Boxborough vs. Somerville","channel":"WGBH 2"},
 {"episode":514,"start_date":"17/05/2014","start_time":"23:00:00:00","gameTitle":"Acton-Boxborough vs. Somerville","channel":"WGBX 44"},
 {"episode":514,"start_date":"18/05/2014","start_time":"10:00:00:00","gameTitle":"Acton-Boxborough vs. Somerville","channel":"WGBH 2"},
 {"episode":514,"start_date":"18/05/2014","start_time":"17:00:00:00","gameTitle":"Acton-Boxborough vs. Somerville","channel":"WGBH 2"},
 {"episode":509,"start_date":"18/05/2014","start_time":"12:00:00:00","gameTitle":"Adv. Math & Science Academy vs. Lexington","channel":"WGBH 2"},
 {"episode":510,"start_date":"18/05/2014","start_time":"12:30:00:00","gameTitle":"Newton North vs. Rockport","channel":"WGBH 2"},
 {"episode":511,"start_date":"18/05/2014","start_time":"13:00:00:00","gameTitle":"Sharon vs. Somerville","channel":"WGBH 2"},
 {"episode":512,"start_date":"18/05/2014","start_time":"13:30:00:00","gameTitle":"Acton-Boxborough vs. Arlington","channel":"WGBH 2"},
 {"episode":513,"start_date":"18/05/2014","start_time":"14:00:00:00","gameTitle":"Lexington vs. Newton North","channel":"WGBH 2"},
 {"episode":514,"start_date":"18/05/2014","start_time":"14:30:00:00","gameTitle":"Acton-Boxborough vs. Somerville","channel":"WGBH 2"},
 {"episode":514,"start_date":"19/05/2014","start_time":"02:30:00:00","gameTitle":"Acton-Boxborough vs. Somerville","channel":"GBH Kids"},
 {"episode":514,"start_date":"19/05/2014","start_time":"20:30:00:00","gameTitle":"Acton-Boxborough vs. Somerville","channel":"GBH Kids"},
 {"episode":514,"start_date":"19/05/2014","start_time":"23:30:00:00","gameTitle":"Acton-Boxborough vs. Somerville","channel":"GBH Kids"},
 {"episode":514,"start_date":"20/05/2014","start_time":"16:30:00:00","gameTitle":"Acton-Boxborough vs. Somerville","channel":"WGBH 2"},
 {"episode":3215,"start_date":"20/05/2014","start_time":"16:00:00:00","gameTitle":"Granite State Challenge","channel":"NHPTV Prime"},
 {"episode":514,"start_date":"20/05/2014","start_time":"17:00:00:00","gameTitle":"Acton-Boxborough vs. Somerville","channel":"NHPTV Prime"},
 {"episode":514,"start_date":"21/05/2014","start_time":"02:30:00:00","gameTitle":"Acton-Boxborough vs. Somerville","channel":"GBH Kids"},
 {"episode":514,"start_date":"21/05/2014","start_time":"20:30:00:00","gameTitle":"Acton-Boxborough vs. Somerville","channel":"GBH Kids"},
 {"episode":514,"start_date":"21/05/2014","start_time":"23:30:00:00","gameTitle":"Acton-Boxborough vs. Somerville","channel":"GBH Kids"},
 {"episode":514,"start_date":"23/05/2014","start_time":"07:30:00:00","gameTitle":"Acton-Boxborough vs. Somerville","channel":"WGBX 44"},
 {"episode":515,"start_date":"24/05/2014","start_time":"18:00:00:00","gameTitle":"Acton-Boxborough vs. Lexington","channel":"WGBH 2"},
 {"episode":1,"start_date":"24/05/2014","start_time":"18:30:00:00","gameTitle":"MA - NH GOVERNOR'S CUP CHALLENGE 2014","channel":"WGBH 2"},
 {"episode":515,"start_date":"24/05/2014","start_time":"23:00:00:00","gameTitle":"Acton-Boxborough vs. Lexington","channel":"WGBX 44"},
 {"episode":1,"start_date":"24/05/2014","start_time":"23:30:00:00","gameTitle":"MA - NH GOVERNOR'S CUP CHALLENGE 2014","channel":"WGBX 44"},
 {"episode":515,"start_date":"25/05/2014","start_time":"10:00:00:00","gameTitle":"Acton-Boxborough vs. Lexington","channel":"WGBH 2"},
 {"episode":1,"start_date":"25/05/2014","start_time":"10:30:00:00","gameTitle":"MA - NH GOVERNOR'S CUP CHALLENGE 2014","channel":"WGBH 2"},
 {"episode":515,"start_date":"25/05/2014","start_time":"17:00:00:00","gameTitle":"Acton-Boxborough vs. Lexington","channel":"WGBH 2"},
 {"episode":1,"start_date":"25/05/2014","start_time":"17:30:00:00","gameTitle":"MA - NH GOVERNOR'S CUP CHALLENGE 2014","channel":"WGBH 2"},
 {"episode":515,"start_date":"26/05/2014","start_time":"02:30:00:00","gameTitle":"Acton-Boxborough vs. Lexington","channel":"GBH Kids"},
 {"episode":515,"start_date":"26/05/2014","start_time":"20:30:00:00","gameTitle":"Acton-Boxborough vs. Lexington","channel":"GBH Kids"},
 {"episode":515,"start_date":"26/05/2014","start_time":"23:30:00:00","gameTitle":"Acton-Boxborough vs. Lexington","channel":"GBH Kids"},
 {"episode":515,"start_date":"27/05/2014","start_time":"16:30:00:00","gameTitle":"Acton-Boxborough vs. Lexington","channel":"WGBH 2"},
 {"episode":1,"start_date":"27/05/2014","start_time":"17:00:00:00","gameTitle":"MA - NH GOVERNOR'S CUP CHALLENGE 2014","channel":"WGBH 2"},
 {"episode":515,"start_date":"27/05/2014","start_time":"16:30:00:00","gameTitle":"Acton-Boxborough vs. Lexington","channel":"NHPTV Prime"},
 {"episode":515,"start_date":"28/05/2014","start_time":"02:30:00:00","gameTitle":"Acton-Boxborough vs. Lexington","channel":"GBH Kids"},
 {"episode":515,"start_date":"28/05/2014","start_time":"20:30:00:00","gameTitle":"Acton-Boxborough vs. Lexington","channel":"GBH Kids"},
 {"episode":515,"start_date":"28/05/2014","start_time":"23:30:00:00","gameTitle":"Acton-Boxborough vs. Lexington","channel":"GBH Kids"},
 {"episode":515,"start_date":"30/05/2014","start_time":"07:30:00:00","gameTitle":"Acton-Boxborough vs. Lexington","channel":"WGBX 44"},
 {"episode":1,"start_date":"30/05/2014","start_time":"08:00:00:00","gameTitle":"MA - NH GOVERNOR'S CUP CHALLENGE 2014","channel":"WGBX 44"}]
